ajdmom/__init__.py
ajdmom/cpp_mom.py
ajdmom/ito_cond_mom.py
ajdmom/ito_mom.py
ajdmom/itos_mom.py
ajdmom/poly.py
ajdmom/utils.py
ajdmom/mdl_1fsv/__init__.py
ajdmom/mdl_1fsv/cmom.py
ajdmom/mdl_1fsv/cond_cmom.py
ajdmom/mdl_1fsv/cov.py
ajdmom/mdl_1fsv/euler.py
ajdmom/mdl_1fsv/mom.py
ajdmom/mdl_1fsvj/__init__.py
ajdmom/mdl_1fsvj/cmom.py
ajdmom/mdl_1fsvj/cov.py
ajdmom/mdl_1fsvj/euler.py
ajdmom/mdl_1fsvj/mom.py
ajdmom/mdl_2fsv/__init__.py
ajdmom/mdl_2fsv/cmom.py
ajdmom/mdl_2fsv/cov.py
ajdmom/mdl_2fsv/euler.py
ajdmom/mdl_2fsv/mom.py
ajdmom/mdl_2fsvj/__init__.py
ajdmom/mdl_2fsvj/cmom.py
ajdmom/mdl_2fsvj/cov.py
ajdmom/mdl_2fsvj/euler.py
ajdmom/mdl_2fsvj/mom.py
ajdmom/mdl_srjd/__init__.py
ajdmom/mdl_srjd/cmom.py
ajdmom/mdl_srjd/cond2_cmom.py
ajdmom/mdl_srjd/cond2_mom.py
ajdmom/mdl_srjd/cond_cmom.py
ajdmom/mdl_srjd/cond_ie_iez_cmom.py
ajdmom/mdl_srjd/cond_ie_iez_mom.py
ajdmom/mdl_srjd/cond_mom.py
ajdmom/mdl_srjd/euler.py
ajdmom/mdl_srjd/iez_cmom.py
ajdmom/mdl_srjd/iez_mom.py
ajdmom/mdl_srjd/mom.py
ajdmom/mdl_svcj/__init__.py
ajdmom/mdl_svcj/cmom.py
ajdmom/mdl_svcj/cond2_cmom.py
ajdmom/mdl_svcj/cond2_mom.py
ajdmom/mdl_svcj/cond_cmom.py
ajdmom/mdl_svcj/cond_ieii_ieziziz_mom.py
ajdmom/mdl_svcj/cond_mom.py
ajdmom/mdl_svcj/euler.py
ajdmom/mdl_svcj/ieziziz_mom.py
ajdmom/mdl_svcj/mom.py
ajdmom/mdl_svij/__init__.py
ajdmom/mdl_svij/cond2_cmom.py
ajdmom/mdl_svij/cond2_mom.py
ajdmom/mdl_svij/euler.py
ajdmom/mdl_svvj/__init__.py
ajdmom/mdl_svvj/cond2_cmom.py
ajdmom/mdl_svvj/cond2_mom.py
ajdmom/mdl_svvj/euler.py
ajdmom-3.0.dist-info/METADATA
ajdmom-3.0.dist-info/WHEEL
ajdmom-3.0.dist-info/licenses/AUTHORS
ajdmom-3.0.dist-info/licenses/LICENSE
ajdmom-3.0.dist-info/RECORD
