Metadata-Version: 2.4
Name: ajdmom
Version: 3.0
Summary: Derivation of moment and covariance formulas for Affine Jump Diffusion processes.
Project-URL: Homepage, https://github.com/xmlongan/ajdmom
Project-URL: Bug Tracker, https://github.com/xmlongan/ajdmom/issues
Author-email: Yan-Feng Wu <wuyf@fudan.edu.cn>
License-File: AUTHORS
License-File: LICENSE
Keywords: Heston model,affine jump diffusion,moment computation,stochastic volatility
Classifier: License :: OSI Approved :: MIT License
Classifier: Operating System :: OS Independent
Classifier: Programming Language :: Python :: 3
Requires-Python: >=3.7
Requires-Dist: numpy
Requires-Dist: pytest
